jack_spam/__init__.py
jack_spam/spam_otp.py
jack_spam-0.1.0.dist-info/METADATA
jack_spam-0.1.0.dist-info/WHEEL
jack_spam-0.1.0.dist-info/top_level.txt
jack_spam-0.1.0.dist-info/RECORD
